scikit_endpoint/__init__.py
scikit_endpoint/base.py
scikit_endpoint/dummy.py
scikit_endpoint/map.py
scikit_endpoint/naive_bayes.py
scikit_endpoint/pipeline.py
scikit_endpoint/utils.py
scikit_endpoint/ensemble/__init__.py
scikit_endpoint/ensemble/_bagging.py
scikit_endpoint/ensemble/_forest.py
scikit_endpoint/ensemble/_gb.py
scikit_endpoint/ensemble/_gb_losses.py
scikit_endpoint/feature_extraction/__init__.py
scikit_endpoint/feature_extraction/_dict_vectorizer.py
scikit_endpoint/feature_extraction/_hash.py
scikit_endpoint/feature_extraction/text.py
scikit_endpoint/feature_selection/__init__.py
scikit_endpoint/feature_selection/_base.py
scikit_endpoint/feature_selection/_variance_threshold.py
scikit_endpoint/impute/__init__.py
scikit_endpoint/impute/_base.py
scikit_endpoint/linear_model/__init__.py
scikit_endpoint/linear_model/_base.py
scikit_endpoint/linear_model/_logistic.py
scikit_endpoint/linear_model/_passive_aggressive.py
scikit_endpoint/linear_model/_perceptron.py
scikit_endpoint/linear_model/_ridge.py
scikit_endpoint/linear_model/_stochastic_gradient.py
scikit_endpoint/metrics/__init__.py
scikit_endpoint/metrics/pairwise.py
scikit_endpoint/preprocessing/__init__.py
scikit_endpoint/preprocessing/_data.py
scikit_endpoint/preprocessing/_encoders.py
scikit_endpoint/preprocessing/_label.py
scikit_endpoint/svm/__init__.py
scikit_endpoint/svm/_classes.py
scikit_endpoint/tree/__init__.py
scikit_endpoint/tree/_classes.py
scikit_endpoint/xgboost/__init__.py
scikit_endpoint/xgboost/_classes.py
tests/__init__.py
tests/test_base.py
tests/test_dummy.py
tests/test_naive_bayes.py
tests/test_pipeline.py
tests/test_utils.py
tests/ensemble/__init__.py
tests/ensemble/test_bagging.py
tests/ensemble/test_extra_trees.py
tests/ensemble/test_gb.py
tests/ensemble/test_import.py
tests/ensemble/test_random_forest.py
tests/feature_extraction/__init__.py
tests/feature_extraction/test_dict_vectorizer.py
tests/feature_extraction/test_import.py
tests/feature_extraction/test_text.py
scikit_endpoint-0.0.3.dist-info/LICENSE
scikit_endpoint-0.0.3.dist-info/METADATA
scikit_endpoint-0.0.3.dist-info/NOTICE
scikit_endpoint-0.0.3.dist-info/WHEEL
scikit_endpoint-0.0.3.dist-info/top_level.txt
scikit_endpoint-0.0.3.dist-info/RECORD
