Metadata-Version: 2.1
Name: scikit-endpoint
Version: 0.0.3
Summary: Fast model predictions for ML Endpoints
Author: Miguel Otero Pedrido
Author-email: miguel.otero.pedrido.1993@gmail.com
License: Apache 2.0
Project-URL: Source Code, https://github.com/MichaelisTrofficus/scikit-endpoint
Classifier: Intended Audience :: Developers
Classifier: Programming Language :: Python
Classifier: Programming Language :: Python :: 3
Classifier: Programming Language :: Python :: 3.8
Classifier: Programming Language :: Python :: 3.9
Classifier: Programming Language :: Python :: 3.10
Classifier: Programming Language :: Python :: 3.11
Classifier: Topic :: Scientific/Engineering
Requires-Python: >=3.9
License-File: LICENSE
License-File: NOTICE
Provides-Extra: tests
Requires-Dist: xgboost (>=1.7.4) ; extra == 'tests'
Requires-Dist: scikit-learn (>=1.2.1) ; extra == 'tests'
Requires-Dist: pandas (>=1.5.3) ; extra == 'tests'
Requires-Dist: numpy (>=1.24.2) ; extra == 'tests'
Requires-Dist: pytest ; extra == 'tests'
Requires-Dist: coverage ; extra == 'tests'
Requires-Dist: nox ; extra == 'tests'
